AUTHORS
CHANGES
LICENSE
MANIFEST.in
README.rst
setup.py
tox.ini
docs/authors.rst
docs/changes.rst
docs/conf.py
docs/contributing.rst
docs/extensions.rst
docs/index.rst
docs/license.rst
docs/quickstart.rst
docs/settings.rst
docs/_static/logo.svg
holocron/__init__.py
holocron/app.py
holocron/content.py
holocron/main.py
holocron/utils.py
holocron.egg-info/PKG-INFO
holocron.egg-info/SOURCES.txt
holocron.egg-info/dependency_links.txt
holocron.egg-info/entry_points.txt
holocron.egg-info/not-zip-safe
holocron.egg-info/requires.txt
holocron.egg-info/top_level.txt
holocron/example/_config.yml
holocron/example/about.mdown
holocron/example/2014/04/20/holocron.mdown
holocron/example/images/young_obiWan.png
holocron/ext/__init__.py
holocron/ext/abc.py
holocron/ext/feed.py
holocron/ext/index.py
holocron/ext/markdown.py
holocron/ext/restructuredtext.py
holocron/ext/sitemap.py
holocron/ext/tags.py
holocron/ext/user_theme.py
holocron/ext/commands/__init__.py
holocron/ext/commands/build.py
holocron/ext/commands/init.py
holocron/ext/commands/serve.py
holocron/theme/static/logo.svg
holocron/theme/static/pygments.css
holocron/theme/static/style.css
holocron/theme/templates/base.html
holocron/theme/templates/counters.html
holocron/theme/templates/document-list.html
holocron/theme/templates/page.html
holocron/theme/templates/post.html
tests/__init__.py
tests/test_app.py
tests/test_content.py
tests/test_main.py
tests/test_utils.py
tests/ext/__init__.py
tests/ext/test_feed.py
tests/ext/test_index.py
tests/ext/test_markdown.py
tests/ext/test_restructuredtext.py
tests/ext/test_sitemap.py
tests/ext/test_tags.py
tests/ext/commands/__init__.py
tests/ext/commands/test_build.py
tests/ext/commands/test_init.py
tests/ext/commands/test_serve.py