Metadata-Version: 1.1
Name: holocron
Version: 0.3.0
Summary: An extendable static blog generator powered by the Force. =/
Home-page: http://github.com/ikalnitsky/holocron/
Author: Igor Kalnitsky
Author-email: igor@kalnitsky.org
License: BSD
Keywords: blog generator static markdown restructuredtext
Platform: UNKNOWN
Classifier: Environment :: Console
Classifier: License :: OSI Approved :: BSD License
Classifier: Operating System :: OS Independent
Classifier: Intended Audience :: End Users/Desktop
Classifier: Intended Audience :: Information Technology
Classifier: Topic :: Internet :: WWW/HTTP
Classifier: Topic :: Terminals
Classifier: Programming Language :: Python
Classifier: Programming Language :: Python :: 3
Classifier: Programming Language :: Python :: 3.3
Classifier: Programming Language :: Python :: 3.4
Classifier: Programming Language :: Python :: 3.5
